chumpy_fork/__init__.py
chumpy_fork/api_compatibility.py
chumpy_fork/ch.py
chumpy_fork/ch_ops.py
chumpy_fork/ch_random.py
chumpy_fork/extras.py
chumpy_fork/linalg.py
chumpy_fork/logic.py
chumpy_fork/monitor.py
chumpy_fork/np_tensordot.py
chumpy_fork/optimization.py
chumpy_fork/optimization_internal.py
chumpy_fork/optional_test_performance.py
chumpy_fork/reordering.py
chumpy_fork/test_ch.py
chumpy_fork/test_inner_composition.py
chumpy_fork/test_linalg.py
chumpy_fork/test_optimization.py
chumpy_fork/testing.py
chumpy_fork/utils.py
chumpy_fork/version.py
chumpy_fork-0.71.dist-info/LICENSE.txt
chumpy_fork-0.71.dist-info/METADATA
chumpy_fork-0.71.dist-info/WHEEL
chumpy_fork-0.71.dist-info/top_level.txt
chumpy_fork-0.71.dist-info/RECORD
