Metadata-Version: 2.1
Name: chumpy_fork
Version: 0.71
Summary: chumpy fork, with latest python, pip and numpy support
Home-page: https://github.com/var/chumpy
Author: Matthew Loper
Author-email: matt.loper@gmail.com
License: MIT
Classifier: Development Status :: 4 - Beta
Classifier: Intended Audience :: Science/Research
Classifier: Topic :: Scientific/Engineering :: Mathematics
Classifier: License :: OSI Approved :: MIT License
Classifier: Programming Language :: Python :: 2
Classifier: Programming Language :: Python :: 2.7
Classifier: Programming Language :: Python :: 3
Classifier: Operating System :: MacOS :: MacOS X
Classifier: Operating System :: POSIX :: Linux
License-File: LICENSE.txt
Requires-Dist: numpy >=1.8.1
Requires-Dist: scipy >=0.13.0
Requires-Dist: six >=1.11.0
